twitch_tools/__init__.py
twitch_tools/token_tools.py
twitch_tools/twitch_follow.py
twitch_tools-0.0.1.dist-info/METADATA
twitch_tools-0.0.1.dist-info/WHEEL
twitch_tools-0.0.1.dist-info/top_level.txt
twitch_tools-0.0.1.dist-info/RECORD
