Metadata-Version: 2.1
Name: twitch-tools
Version: 0.0.1
Summary: Package with lots of twitch tools.
Home-page: UNKNOWN
Author: Pipam
Author-email: <churrerico100@gmail.com>
License: UNKNOWN
Keywords: python,twitch,bot,tools,follow
Platform: UNKNOWN
Classifier: Development Status :: 2 - Pre-Alpha
Classifier: Intended Audience :: Developers
Classifier: Programming Language :: Python :: 3
Classifier: Operating System :: Unix
Classifier: Operating System :: MacOS :: MacOS X
Classifier: Operating System :: Microsoft :: Windows
Requires-Dist: requests
